langchain_deepai/__init__.py
langchain_deepai/keys.py
langchain_deepai/styles.py
langchain_deepai/core/__init__.py
langchain_deepai/core/authentication.py
langchain_deepai/core/providers.py
langchain_deepai/core/utils.py
langchain_deepai/images/__init__.py
langchain_deepai/images/image_generation.py
langchain_deepai/speech/__init__.py
langchain_deepai/speech/speech_to_text.py
langchain_deepai/speech/text_to_speech.py
langchain_deepai/text/__init__.py
langchain_deepai/text/base.py
langchain_deepai/text/specialized.py
langchain_deepai-0.0.6.dist-info/licenses/LICENSE
langchain_deepai-0.0.6.dist-info/METADATA
langchain_deepai-0.0.6.dist-info/WHEEL
langchain_deepai-0.0.6.dist-info/top_level.txt
langchain_deepai-0.0.6.dist-info/RECORD
