Metadata-Version: 2.4
Name: langchain-deepai
Version: 0.0.6
Summary: LangChain integration for DeepAI API with chat, images, and speech capabilities
Author: AIMLStudent
License: MIT
Project-URL: Homepage, https://github.com/your-org/langchain-deepai
Project-URL: Documentation, https://langchain-deepai.readthedocs.io
Project-URL: Repository, https://github.com/your-org/langchain-deepai
Project-URL: Bug Tracker, https://github.com/your-org/langchain-deepai/issues
Keywords: langchain,deepai,ai,chat,image-generation,text-to-speech,speech-to-text,machine-learning
Classifier: Development Status :: 4 - Beta
Classifier: Intended Audience :: Developers
Classifier: License :: OSI Approved :: MIT License
Classifier: Operating System :: OS Independent
Classifier: Programming Language :: Python :: 3
Classifier: Programming Language :: Python :: 3.8
Classifier: Programming Language :: Python :: 3.9
Classifier: Programming Language :: Python :: 3.10
Classifier: Programming Language :: Python :: 3.11
Classifier: Programming Language :: Python :: 3.12
Classifier: Topic :: Scientific/Engineering :: Artificial Intelligence
Classifier: Topic :: Software Development :: Libraries :: Python Modules
Requires-Python: >=3.8
License-File: LICENSE
Requires-Dist: langchain-core>=0.1.0
Requires-Dist: requests>=2.25.0
Requires-Dist: pydantic>=1.10.0
Requires-Dist: typing-extensions>=4.0.0
Provides-Extra: dev
Requires-Dist: pytest>=7.0.0; extra == "dev"
Requires-Dist: pytest-asyncio>=0.21.0; extra == "dev"
Requires-Dist: black>=22.0.0; extra == "dev"
Requires-Dist: isort>=5.12.0; extra == "dev"
Requires-Dist: flake8>=6.0.0; extra == "dev"
Requires-Dist: mypy>=1.0.0; extra == "dev"
Provides-Extra: image
Requires-Dist: Pillow>=8.0.0; extra == "image"
Provides-Extra: all
Requires-Dist: langchain-deepai[dev,image]; extra == "all"
Dynamic: license-file
